certcheck/__init__.py
certcheck-0.1.data/scripts/certcheck
certcheck-0.1.dist-info/METADATA
certcheck-0.1.dist-info/WHEEL
certcheck-0.1.dist-info/top_level.txt
certcheck-0.1.dist-info/RECORD
